{
	"success": true,
	"data": [{
		"title": "三生三世 十里桃花",
		"smallimgUrl":"//upload-images.jianshu.io/upload_images/12309992-54fcd2c5383cfd13.jpg?imageMogr2/auto-orient/strip|imageView2/1/w/300/h/240",
		"bigImgUrl":"//upload-images.jianshu.io/upload_images/5282108-73fa31bf61d9f817.jpg?imageMogr2/auto-orient/strip%7CimageView2/2/w/500/format/webp",
		"content":[
			{
				"info":"去年冬天，女儿寒假时在她爸爸那儿住了几天，那时，正好她奶奶从农村老家上来小住。一天，女儿回到我这里说，她奶奶很认真地托她转达对我的一番话，她说过去我们曾发生过些不愉快，也许我误解了她，她对我完全没有恶意，叫我不要记恨她，并给我道歉。"
				
			},
			{
				"info":"去年冬天，女儿寒假时在她爸爸那儿住了几天，那时，正好她奶奶从农村老家上来小住。一天，女儿回到我这里说，她奶奶很认真地托她转达对我的一番话，她说过去我们曾发生过些不愉快，也许我误解了她，她对我完全没有恶意，叫我不要记恨她，并给我道歉。"
				
			},
			{
				"info":"去年冬天，女儿寒假时在她爸爸那儿住了几天，那时，正好她奶奶从农村老家上来小住。一天，女儿回到我这里说，她奶奶很认真地托她转达对我的一番话，她说过去我们曾发生过些不愉快，也许我误解了她，她对我完全没有恶意，叫我不要记恨她，并给我道歉。"
				
			}
			
		]

		
	}]
}